{
  "hash": "e26a3a15",
  "configHash": "f5b95ca9",
  "lockfileHash": "1b952546",
  "browserHash": "f1bc9e15",
  "optimized": {
    "react": {
      "src": "../../node_modules/react/index.js",
      "file": "react.js",
      "fileHash": "96702a81",
      "needsInterop": true
    },
    "react-dom": {
      "src": "../../node_modules/react-dom/index.js",
      "file": "react-dom.js",
      "fileHash": "f2dc26fa",
      "needsInterop": true
    },
    "react/jsx-dev-runtime": {
      "src": "../../node_modules/react/jsx-dev-runtime.js",
      "file": "react_jsx-dev-runtime.js",
      "fileHash": "c4c8adba",
      "needsInterop": true
    },
    "react/jsx-runtime": {
      "src": "../../node_modules/react/jsx-runtime.js",
      "file": "react_jsx-runtime.js",
      "fileHash": "02a0a106",
      "needsInterop": true
    },
    "@tanstack/react-query": {
      "src": "../../node_modules/@tanstack/react-query/build/modern/index.js",
      "file": "@tanstack_react-query.js",
      "fileHash": "23362d1f",
      "needsInterop": false
    },
    "axios": {
      "src": "../../node_modules/axios/index.js",
      "file": "axios.js",
      "fileHash": "9e59d1cd",
      "needsInterop": false
    },
    "country-state-city": {
      "src": "../../node_modules/country-state-city/lib/index.js",
      "file": "country-state-city.js",
      "fileHash": "1a0cd75e",
      "needsInterop": false
    },
    "currency-codes": {
      "src": "../../node_modules/currency-codes/index.js",
      "file": "currency-codes.js",
      "fileHash": "31b38a65",
      "needsInterop": true
    },
    "framer-motion": {
      "src": "../../node_modules/framer-motion/dist/es/index.mjs",
      "file": "framer-motion.js",
      "fileHash": "aa0c2481",
      "needsInterop": false
    },
    "joi": {
      "src": "../../node_modules/joi/dist/joi-browser.min.js",
      "file": "joi.js",
      "fileHash": "e536b08c",
      "needsInterop": true
    },
    "nprogress": {
      "src": "../../node_modules/nprogress/nprogress.js",
      "file": "nprogress.js",
      "fileHash": "ff6ce6fe",
      "needsInterop": true
    },
    "react-dom/client": {
      "src": "../../node_modules/react-dom/client.js",
      "file": "react-dom_client.js",
      "fileHash": "4cba4e5b",
      "needsInterop": true
    },
    "react-loading-skeleton": {
      "src": "../../node_modules/react-loading-skeleton/dist/index.js",
      "file": "react-loading-skeleton.js",
      "fileHash": "c3e95984",
      "needsInterop": false
    },
    "react-phone-number-input": {
      "src": "../../node_modules/react-phone-number-input/min/index.js",
      "file": "react-phone-number-input.js",
      "fileHash": "9c3f393a",
      "needsInterop": false
    },
    "react-router-dom": {
      "src": "../../node_modules/react-router-dom/dist/index.mjs",
      "file": "react-router-dom.js",
      "fileHash": "22695f6c",
      "needsInterop": false
    },
    "react-select": {
      "src": "../../node_modules/react-select/dist/react-select.esm.js",
      "file": "react-select.js",
      "fileHash": "f24fd6cf",
      "needsInterop": false
    },
    "react-toastify": {
      "src": "../../node_modules/react-toastify/dist/index.mjs",
      "file": "react-toastify.js",
      "fileHash": "24dfb848",
      "needsInterop": false
    },
    "recharts": {
      "src": "../../node_modules/recharts/es6/index.js",
      "file": "recharts.js",
      "fileHash": "008ceb0a",
      "needsInterop": false
    }
  },
  "chunks": {
    "chunk-LNJWJNFR": {
      "file": "chunk-LNJWJNFR.js"
    },
    "chunk-7I2UKMSJ": {
      "file": "chunk-7I2UKMSJ.js"
    },
    "chunk-C76DDT7O": {
      "file": "chunk-C76DDT7O.js"
    },
    "chunk-P6RTVJOB": {
      "file": "chunk-P6RTVJOB.js"
    },
    "chunk-G3PMV62Z": {
      "file": "chunk-G3PMV62Z.js"
    }
  }
}